environments/build_images.py
magique/__init__.py
magique/ai/__init__.py
magique/ai/__main__.py
magique/ai/constant.py
magique/ai/toolset.py
magique/ai/endpoint/__init__.py
magique/ai/endpoint/__main__.py
magique/ai/endpoint/core.py
magique/ai/endpoint/hub.py
magique/ai/rag/__init__.py
magique/ai/rag/__main__.py
magique/ai/rag/build.py
magique/ai/rag/vectordb.py
magique/ai/rag/wrap.py
magique/ai/tools/__init__.py
magique/ai/tools/file_manager/__init__.py
magique/ai/tools/file_manager/__main__.py
magique/ai/tools/file_manager/core.py
magique/ai/tools/file_transfer/__init__.py
magique/ai/tools/file_transfer/__main__.py
magique/ai/tools/file_transfer/client.py
magique/ai/tools/file_transfer/worker.py
magique/ai/tools/python/__init__.py
magique/ai/tools/python/__main__.py
magique/ai/tools/python/python_interpreter.py
magique/ai/tools/r/__init__.py
magique/ai/tools/r/__main__.py
magique/ai/tools/r/_rinter.py
magique/ai/tools/r/r_interpreter.py
magique/ai/tools/scraper/__init__.py
magique/ai/tools/scraper/__main__.py
magique/ai/tools/shell/__init__.py
magique/ai/tools/shell/__main__.py
magique/ai/tools/shell/_shell.py
magique/ai/tools/shell/shell.py
magique/ai/tools/vector_rag/__init__.py
magique/ai/tools/vector_rag/__main__.py
magique/ai/tools/vector_rag/rag.py
magique/ai/tools/web_browse/__init__.py
magique/ai/tools/web_browse/__main__.py
magique/ai/tools/web_browse/duckduckgo.py
magique/ai/tools/web_browse/web_crawl.py
magique/ai/utils/__init__.py
magique/ai/utils/llm.py
magique/ai/utils/log.py
magique/ai/utils/remote.py
magique/ai/utils/text.py
tests/conftest.py
tests/test_file_manager.py
tests/test_remote_toolset.py
magique_ai-0.4.3.dist-info/METADATA
magique_ai-0.4.3.dist-info/WHEEL
magique_ai-0.4.3.dist-info/top_level.txt
magique_ai-0.4.3.dist-info/RECORD
