Metadata-Version: 2.4
Name: magique-ai
Version: 0.4.3
Summary: Toolset for AI Agents, provide service via magique message transfer server.
Author-email: Weize Xu <vet.xwz@gmail.com>
License: MIT
Requires-Python: >=3.10
Requires-Dist: magique>=0.6.5
Requires-Dist: executor-engine>=0.3.3
Requires-Dist: diskcache
Requires-Dist: httpx>=0.28.1
Requires-Dist: fire>=0.7.0
Requires-Dist: lancedb>=0.20.0
Requires-Dist: crawl4ai>=0.5.0
Requires-Dist: duckduckgo-search>=7.1.1
Requires-Dist: loguru>=0.7.3
Requires-Dist: openai>=1.58.1
Requires-Dist: PyMuPDF>=1.25.5
Requires-Dist: matplotlib>=3.10.3
Provides-Extra: dev
Requires-Dist: pytest-asyncio>=0.24.0; extra == "dev"
Requires-Dist: pytest>=8.3.4; extra == "dev"
Requires-Dist: pytest-cov>=6.0.0; extra == "dev"
